cloudshell/__init__.py
cloudshell/networking/__init__.py
cloudshell/networking/ipinfusion/__init__.py
cloudshell/networking/ipinfusion/autoload/__init__.py
cloudshell/networking/ipinfusion/autoload/ipinfusion_generic_snmp_autoload.py
cloudshell/networking/ipinfusion/autoload/snmp_system_info.py
cloudshell/networking/ipinfusion/cli/__init__.py
cloudshell/networking/ipinfusion/cli/ipinfusion_cli_handler.py
cloudshell/networking/ipinfusion/cli/ipinfusion_command_modes.py
cloudshell/networking/ipinfusion/command_actions/__init__.py
cloudshell/networking/ipinfusion/command_actions/enable_disable_snmp_actions.py
cloudshell/networking/ipinfusion/command_actions/save_restore_actions.py
cloudshell/networking/ipinfusion/command_actions/system_actions.py
cloudshell/networking/ipinfusion/command_templates/__init__.py
cloudshell/networking/ipinfusion/command_templates/configuration.py
cloudshell/networking/ipinfusion/command_templates/enable_disable_snmp.py
cloudshell/networking/ipinfusion/command_templates/system.py
cloudshell/networking/ipinfusion/flows/__init__.py
cloudshell/networking/ipinfusion/flows/ipinfusion_autoload_flow.py
cloudshell/networking/ipinfusion/flows/ipinfusion_configuration_flow.py
cloudshell/networking/ipinfusion/flows/ipinfusion_disable_snmp_flow.py
cloudshell/networking/ipinfusion/flows/ipinfusion_enable_snmp_flow.py
cloudshell/networking/ipinfusion/flows/ipinfusion_run_command_flow.py
cloudshell/networking/ipinfusion/flows/ipinfusion_state_flow.py
cloudshell/networking/ipinfusion/helpers/__init__.py
cloudshell/networking/ipinfusion/helpers/exceptions.py
cloudshell/networking/ipinfusion/mibs/__init__.py
cloudshell/networking/ipinfusion/snmp/__init__.py
cloudshell/networking/ipinfusion/snmp/ipinfusion_snmp_handler.py
tests/__init__.py
tests/cloudshell/__init__.py
tests/cloudshell/networking/__init__.py
tests/cloudshell/networking/ipinfusion/__init__.py
tests/cloudshell/networking/ipinfusion/flows/__init__.py
cloudshell_networking_ipinfusion-1.0.0.dist-info/METADATA
cloudshell_networking_ipinfusion-1.0.0.dist-info/WHEEL
cloudshell_networking_ipinfusion-1.0.0.dist-info/top_level.txt
cloudshell_networking_ipinfusion-1.0.0.dist-info/RECORD
